pygamedui/__init__.py
pygamedui/anchor.py
pygamedui/container.py
pygamedui/layout.py
pygamedui/layouts.py
pygamedui/ui_element.py
pygamedui/widgets.py
pygamedui/layouts/stack_layout.py
pygamedui-0.0.1.dist-info/licenses/LICENSE
pygamedui-0.0.1.dist-info/METADATA
pygamedui-0.0.1.dist-info/WHEEL
pygamedui-0.0.1.dist-info/top_level.txt
pygamedui-0.0.1.dist-info/RECORD
