Metadata-Version: 2.4
Name: pygamedui
Version: 0.0.1
Summary: A GUI framework for pygame
Author-email: Wojciech Bulcewicz <bulcewiczwojciech@gmail.com>
License: Copyright (c) 2025 PyGameDGUI
Project-URL: Homepage, https://github.com/wowek2/pygame_dui
Classifier: Development Status :: 3 - Alpha
Classifier: License :: OSI Approved :: MIT License
Classifier: Programming Language :: Python :: 3
Classifier: Operating System :: OS Independent
Classifier: Topic :: Software Development :: Libraries
Classifier: Topic :: Games/Entertainment
Requires-Python: >=3.6
License-File: LICENSE
Requires-Dist: pygame>=2.0.0
Dynamic: license-file
